examples/__init__.py
examples/test.py
examples/SEIHR_2_age_group/__init__.py
examples/SEIHR_2_age_group/seihr_2_ag_main.py
examples/SEIHR_2_age_group/simulation_seihr.py
examples/SEIR_no_age_groups/__init__.py
examples/SEIR_no_age_groups/model_seir.py
examples/SEIR_no_age_groups/sampler_seir.py
examples/SEIR_no_age_groups/seir_no_ag_main.py
examples/SEIR_no_age_groups/simulation_seir.py
examples/contact_sensitivity/__init__.py
examples/contact_sensitivity/contact_main.py
examples/contact_sensitivity/sampler_contact.py
examples/contact_sensitivity/sensitivity_model_contact.py
examples/contact_sensitivity/simulation_contact.py
examples/utils/__init__.py
examples/utils/dataloader_16_ag.py
examples/vaccinated_sensitivity/__init__.py
examples/vaccinated_sensitivity/sampler_vaccinated.py
examples/vaccinated_sensitivity/sensitivity_model_vaccinated.py
examples/vaccinated_sensitivity/simulation_vacc.py
examples/vaccinated_sensitivity/vaccinated_main.py
src/__init__.py
src/dataloader.py
src/plotter.py
src/simulation_base.py
src/model/__init__.py
src/model/epidemic_model.py
src/model/matrix_generator.py
src/model/model_base.py
src/model/r0.py
src/sensitivity/__init__.py
src/sensitivity/prcc.py
src/sensitivity/sampler_base.py
src/sensitivity/sensitivity_model_base.py
src/sensitivity/target_calc/__init__.py
src/sensitivity/target_calc/final_size_calc.py
src/sensitivity/target_calc/output_generator.py
src/sensitivity/target_calc/peak_calc.py
src/sensitivity/target_calc/target_calc_base.py
epimodel_sensitivity-0.1.0.dist-info/METADATA
epimodel_sensitivity-0.1.0.dist-info/WHEEL
epimodel_sensitivity-0.1.0.dist-info/top_level.txt
epimodel_sensitivity-0.1.0.dist-info/RECORD
